Workbook

Sheet Data
A1: OrderID | B1: Date | C1: Region | D1: SalesRep | E1: Product | F1: Category | G1: Units | H1: UnitPrice | I1: Revenue | J1: Cost | K1: Profit
A2: ORD-1001 | B2: 45772 | C2: North | D2: Amit Sharma | E2: Laptop | F2: Electronics | G2: 12 | H2: 55000 | I2: 660000 | J2: 399304 | K2: 260696
A3: ORD-1002 | B3: 45702 | C3: North | D3: Priya Verma | E3: Keyboard | F3: Accessories | G3: 12 | H3: 2500 | I3: 30000 | J3: 21853 | K3: 8147
A4: ORD-1003 | B4: 45916 | C4: North | D4: Amit Sharma | E4: Laptop | F4: Electronics | G4: 2 | H4: 55000 | I4: 110000 | J4: 65310 | K4: 44690
A5: ORD-1004 | B5: 45872 | C5: South | D5: Ravi Nair | E5: Keyboard | F5: Accessories | G5: 11 | H5: 2500 | I5: 27500 | J5: 18982 | K5: 8518
A6: ORD-1005 | B6: 45661 | C6: West | D6: Vikram Mehta | E6: Headphones | F6: Accessories | G6: 5 | H6: 3500 | I6: 17500 | J6: 12458 | K6: 5042
A7: ORD-1006 | B7: 45830 | C7: West | D7: Vikram Mehta | E7: Tablet | F7: Electronics | G7: 5 | H7: 18000 | I7: 90000 | J7: 52299 | K7: 37701
A8: ORD-1007 | B8: 45834 | C8: North | D8: Priya Verma | E8: Monitor | F8: Electronics | G8: 2 | H8: 14000 | I8: 28000 | J8: 17410 | K8: 10590
A9: ORD-1008 | B9: 45851 | C9: North | D9: Amit Sharma | E9: Keyboard | F9: Accessories | G9: 8 | H9: 2500 | I9: 20000 | J9: 13145 | K9: 6855
A10: ORD-1009 | B10: 45843 | C10: East | D10: Sourav Das | E10: Keyboard | F10: Accessories | G10: 10 | H10: 2500 | I10: 25000 | J10: 18177 | K10: 6823
A11: ORD-1010 | B11: 45806 | C11: North | D11: Amit Sharma | E11: Laptop | F11: Electronics | G11: 11 | H11: 55000 | I11: 605000 | J11: 360326 | K11: 244674
A12: ORD-1011 | B12: 45983 | C12: South | D12: Divya Menon | E12: Laptop | F12: Electronics | G12: 7 | H12: 55000 | I12: 385000 | J12: 233154 | K12: 151846
A13: ORD-1012 | B13: 45794 | C13: South | D13: Ravi Nair | E13: Tablet | F13: Electronics | G13: 6 | H13: 18000 | I13: 108000 | J13: 63925 | K13: 44075
... A501: ORD-1500 | B501: 45993 | C501: South | D501: Ravi Nair | E501: Monitor | F501: Electronics | G501: 1 | H501: 14000 | I501: 14000 | J501: 10479 | K501: 3521

Sheet Dashboard
A1: Sales Performance Dashboard — 2025
A2: All figures below are live Excel formulas reading the Data sheet — change any row and the dashboard updates.
B3: Total Revenue | D3: Total Orders | F3: Avg Order Value | H3: Total Profit | J3: Top Product
B4: =SUM(Data!I2:I501) | D4: =COUNTA(Data!A2:A501) | F4: =AVERAGE(Data!I2:I501) | H4: =SUM(Data!K2:K501) | J4: =XLOOKUP(MAX(K11:K16),K11:K16,J11:J16)
A9: Monthly trend (formula-driven) | F9: Revenue by region | J9: Revenue by product
A10: Month | B10: Revenue | C10: Orders | D10: Avg Order | F10: Region | G10: Revenue | H10: Orders | J10: Product | K10: Revenue
A11: 45658 | B11: =SUMIFS(Data!I$2:I$501,Data!B$2:B$501,">="&A11,Data!B$2:B$501,"<"&EDATE(A11,1)) | C11: =COUNTIFS(Data!B$2:B$501,">="&A11,Data!B$2:B$501,"<"&EDATE(A11,1)) | D11: =IF(C11=0,0,B11/C11) | F11: North | G11: =SUMIFS(Data!I$2:I$501,Data!C$2:C$501,F11) | H11: =COUNTIFS(Data!C$2:C$501,F11) | J11: Laptop | K11: =SUMIFS(Data!I$2:I$501,Data!E$2:E$501,J11)
A12: 45689 | B12: =SUMIFS(Data!I$2:I$501,Data!B$2:B$501,">="&A12,Data!B$2:B$501,"<"&EDATE(A12,1)) | C12: =COUNTIFS(Data!B$2:B$501,">="&A12,Data!B$2:B$501,"<"&EDATE(A12,1)) | D12: =IF(C12=0,0,B12/C12) | F12: South | G12: =SUMIFS(Data!I$2:I$501,Data!C$2:C$501,F12) | H12: =COUNTIFS(Data!C$2:C$501,F12) | J12: Smartphone | K12: =SUMIFS(Data!I$2:I$501,Data!E$2:E$501,J12)
A13: 45717 | B13: =SUMIFS(Data!I$2:I$501,Data!B$2:B$501,">="&A13,Data!B$2:B$501,"<"&EDATE(A13,1)) | C13: =COUNTIFS(Data!B$2:B$501,">="&A13,Data!B$2:B$501,"<"&EDATE(A13,1)) | D13: =IF(C13=0,0,B13/C13) | F13: East | G13: =SUMIFS(Data!I$2:I$501,Data!C$2:C$501,F13) | H13: =COUNTIFS(Data!C$2:C$501,F13) | J13: Tablet | K13: =SUMIFS(Data!I$2:I$501,Data!E$2:E$501,J13)
A14: 45748 | B14: =SUMIFS(Data!I$2:I$501,Data!B$2:B$501,">="&A14,Data!B$2:B$501,"<"&EDATE(A14,1)) | C14: =COUNTIFS(Data!B$2:B$501,">="&A14,Data!B$2:B$501,"<"&EDATE(A14,1)) | D14: =IF(C14=0,0,B14/C14) | F14: West | G14: =SUMIFS(Data!I$2:I$501,Data!C$2:C$501,F14) | H14: =COUNTIFS(Data!C$2:C$501,F14) | J14: Monitor | K14: =SUMIFS(Data!I$2:I$501,Data!E$2:E$501,J14)
A15: 45778 | B15: =SUMIFS(Data!I$2:I$501,Data!B$2:B$501,">="&A15,Data!B$2:B$501,"<"&EDATE(A15,1)) | C15: =COUNTIFS(Data!B$2:B$501,">="&A15,Data!B$2:B$501,"<"&EDATE(A15,1)) | D15: =IF(C15=0,0,B15/C15) | J15: Headphones | K15: =SUMIFS(Data!I$2:I$501,Data!E$2:E$501,J15)
A16: 45809 | B16: =SUMIFS(Data!I$2:I$501,Data!B$2:B$501,">="&A16,Data!B$2:B$501,"<"&EDATE(A16,1)) | C16: =COUNTIFS(Data!B$2:B$501,">="&A16,Data!B$2:B$501,"<"&EDATE(A16,1)) | D16: =IF(C16=0,0,B16/C16) | J16: Keyboard | K16: =SUMIFS(Data!I$2:I$501,Data!E$2:E$501,J16)
A17: 45839 | B17: =SUMIFS(Data!I$2:I$501,Data!B$2:B$501,">="&A17,Data!B$2:B$501,"<"&EDATE(A17,1)) | C17: =COUNTIFS(Data!B$2:B$501,">="&A17,Data!B$2:B$501,"<"&EDATE(A17,1)) | D17: =IF(C17=0,0,B17/C17)
A18: 45870 | B18: =SUMIFS(Data!I$2:I$501,Data!B$2:B$501,">="&A18,Data!B$2:B$501,"<"&EDATE(A18,1)) | C18: =COUNTIFS(Data!B$2:B$501,">="&A18,Data!B$2:B$501,"<"&EDATE(A18,1)) | D18: =IF(C18=0,0,B18/C18)
A19: 45901 | B19: =SUMIFS(Data!I$2:I$501,Data!B$2:B$501,">="&A19,Data!B$2:B$501,"<"&EDATE(A19,1)) | C19: =COUNTIFS(Data!B$2:B$501,">="&A19,Data!B$2:B$501,"<"&EDATE(A19,1)) | D19: =IF(C19=0,0,B19/C19)
A20: 45931 | B20: =SUMIFS(Data!I$2:I$501,Data!B$2:B$501,">="&A20,Data!B$2:B$501,"<"&EDATE(A20,1)) | C20: =COUNTIFS(Data!B$2:B$501,">="&A20,Data!B$2:B$501,"<"&EDATE(A20,1)) | D20: =IF(C20=0,0,B20/C20)
A21: 45962 | B21: =SUMIFS(Data!I$2:I$501,Data!B$2:B$501,">="&A21,Data!B$2:B$501,"<"&EDATE(A21,1)) | C21: =COUNTIFS(Data!B$2:B$501,">="&A21,Data!B$2:B$501,"<"&EDATE(A21,1)) | D21: =IF(C21=0,0,B21/C21)
A22: 45992 | B22: =SUMIFS(Data!I$2:I$501,Data!B$2:B$501,">="&A22,Data!B$2:B$501,"<"&EDATE(A22,1)) | C22: =COUNTIFS(Data!B$2:B$501,">="&A22,Data!B$2:B$501,"<"&EDATE(A22,1)) | D22: =IF(C22=0,0,B22/C22)
